langchain_mcp_tools/__init__.py
langchain_mcp_tools/langchain_mcp_tools.py
langchain_mcp_tools/py.typed
langchain_mcp_tools/tool_adapter.py
langchain_mcp_tools/transport_utils.py
langchain_mcp_tools-0.2.13.dist-info/licenses/LICENSE
langchain_mcp_tools-0.2.13.dist-info/METADATA
langchain_mcp_tools-0.2.13.dist-info/WHEEL
langchain_mcp_tools-0.2.13.dist-info/top_level.txt
langchain_mcp_tools-0.2.13.dist-info/RECORD
