Metadata-Version: 2.4
Name: langchain-mcp-tools
Version: 0.2.13
Summary: Model Context Protocol (MCP) To LangChain Tools Conversion Utility
Project-URL: Bug Tracker, https://github.com/hideya/langchain-mcp-tools-py/issues
Project-URL: Source Code, https://github.com/hideya/langchain-mcp-tools-py
Keywords: modelcontextprotocol,mcp,mcp-client,langchain,langchain-python,tool-call,tool-calling,python
Requires-Python: >=3.11
License-File: LICENSE
Requires-Dist: jsonschema-pydantic>=0.6
Requires-Dist: langchain>=0.3.26
Requires-Dist: langchain-core>=0.3.66
Requires-Dist: mcp>=1.9.4
Provides-Extra: dev
Requires-Dist: dotenv>=0.9.9; extra == "dev"
Requires-Dist: fastapi>=0.115.12; extra == "dev"
Requires-Dist: fastmcp>=2.10.1; extra == "dev"
Requires-Dist: pyjwt>=2.10.1; extra == "dev"
Requires-Dist: langchain-anthropic>=0.3.17; extra == "dev"
Requires-Dist: langchain-cerebras>=0.5.0; extra == "dev"
Requires-Dist: langchain-google-genai>=2.1.5; extra == "dev"
Requires-Dist: langchain-groq>=0.3.7; extra == "dev"
Requires-Dist: langchain-openai>=0.3.0; extra == "dev"
Requires-Dist: langchain-xai>=0.2.4; extra == "dev"
Requires-Dist: langgraph>=0.2.62; extra == "dev"
Requires-Dist: pytest>=8.3.4; extra == "dev"
Requires-Dist: pytest-asyncio>=0.25.2; extra == "dev"
Requires-Dist: websockets>=15.0.1; extra == "dev"
Dynamic: license-file
